flopth/__init__.py
flopth/helper.py
flopth/model_viewer.py
flopth/settings.py
flopth/utils.py
flopth-0.1.6.dist-info/METADATA
flopth-0.1.6.dist-info/WHEEL
flopth-0.1.6.dist-info/entry_points.txt
flopth-0.1.6.dist-info/licenses/LICENSE
flopth-0.1.6.dist-info/RECORD
