Metadata-Version: 2.3
Name: flopth
Version: 0.1.6
Summary: A program to calculate FLOPs and Parameters of Pytorch models
Requires-Python: >=3.8
Requires-Dist: numpy>=1.20
Requires-Dist: tabulate>=0.9.0
Requires-Dist: torch>=1.6.0
Requires-Dist: torchvision>=0.20.1
